{
  "patient_id": "PAT_2159",
  "severity": "low",
  "num_mutations": 1,
  "genes_analyzed": [
    "TP53",
    "BRCA1",
    "BRCA2",
    "KRAS",
    "EGFR",
    "PIK3CA",
    "APC",
    "PTEN",
    "RB1",
    "MYC",
    "ALK",
    "BRAF"
  ],
  "genes_with_mutations": [
    "BRAF"
  ],
  "cancer_type": "Melanome",
  "age": 56,
  "sex": "F",
  "data_source": "TCGA_PanCancer_Atlas",
  "is_real_data": true,
  "original_patient_id": "TCGA-EB-A3Y6",
  "original_study": "skcm_tcga_pan_can_atlas_2018"
}