{
  "patient_id": "PAT_0038",
  "severity": "low",
  "num_mutations": 3,
  "genes_analyzed": [
    "TP53",
    "BRCA1",
    "BRCA2",
    "KRAS",
    "EGFR",
    "PIK3CA",
    "APC",
    "PTEN",
    "RB1",
    "MYC",
    "ALK",
    "BRAF"
  ],
  "genes_with_mutations": [
    "BRCA1",
    "BRCA2",
    "PIK3CA"
  ],
  "cancer_type": "Sein",
  "age": 43,
  "sex": "F",
  "data_source": "TCGA_PanCancer_Atlas",
  "is_real_data": true,
  "original_patient_id": "TCGA-C8-A12T",
  "original_study": "brca_tcga_pan_can_atlas_2018"
}